stoic_trace_cockpit-2021.9.2.data/scripts/manage.py
stoic_trace_cockpit-2021.9.2.data/scripts/release.py
trace_cockpit/__init__.py
trace_cockpit/admin.py
trace_cockpit/html.py
trace_cockpit/htmlutils.py
trace_cockpit/middleware.py
trace_cockpit/models.py
trace_cockpit/testutils.py
trace_cockpit/trace_to_json.py
stoic_trace_cockpit-2021.9.2.dist-info/LICENSE
stoic_trace_cockpit-2021.9.2.dist-info/METADATA
stoic_trace_cockpit-2021.9.2.dist-info/WHEEL
stoic_trace_cockpit-2021.9.2.dist-info/top_level.txt
stoic_trace_cockpit-2021.9.2.dist-info/RECORD
