Metadata-Version: 2.1
Name: stoic-trace-cockpit
Version: 2021.9.2
Summary: Stoic Trace Cockpit
Home-page: https://github.com/guettli/stoic-trace-cockpit
Author: Thomas Guettler
Author-email: guettliml.stoic-trace-cockpit@thomas-guettler.de
License: UNKNOWN
Platform: UNKNOWN
Classifier: Environment :: Web Environment
Classifier: Framework :: Django
Classifier: License :: OSI Approved :: MIT License
Classifier: Programming Language :: Python :: 3
Requires-Python: >=3.8
License-File: LICENSE
Requires-Dist: django
Requires-Dist: django-ordered-model
Requires-Dist: hunter
Requires-Dist: stoic-html
